Workbook

Sheet Dashboard
A3: INPUTS
A4: Quantidade (un.) | B4: 5000 | C4: Semanas | D4: 24 | E4: Pagamento | F4: Pix
A5: Múltiplos de 1.000 (1k a 20k) | C5: Múltiplos de 4 (4 a 52) | E5: Pix, Boleto ou Cartão
A7: ECONOMICS | D7: RESUMO RÁPIDO
A8: CUSTOS | D8: Preço Total | F8: Preço Unitário | H8: Desconto Total
A9: Custo GPC Unitário | B9: =INDEX(Premissas!B34:B53,MATCH(B4,Premissas!A34:A53,0)) -> 0.2998 | D9: =B24 -> 49560.273 | F9: =B25 -> 1.6520091 | H9: =B22 -> 0.37271328
A10: Custo Produção Total | B10: =B9*B4*INDEX(Premissas!E34:E53,MATCH(B4,Premissas!A34:A53,0)) -> 1499
A11: Frete | B11: =INDEX(Premissas!D34:D53,MATCH(B4,Premissas!A34:A53,0)) -> 357.19
A12: Custo Total (Prod+Frete) | B12: =B10+B11 -> 1856.19 | D12: Lucro Bruto | F12: Margem Líquida | H12: Custo Total
A13: PREÇO SEM DESCONTO | D13: =B37 -> 23059.448 | F13: =B38 -> 0.4652809 | H13: =B12*B23 -> 11137.14
A14: Margem Alvo | B14: =INDEX(Premissas!C34:C53,MATCH(B4,Premissas!A34:A53,0)) -> 0.5
A15: Denominador | B15: =1-B14-Premissas!B4-Premissas!B5-Premissas!B6 -> 0.19
A16: Preço Unit. (4 sem, s/ desc.) | B16: =B12/B4/B15 -> 1.9538842 | D16: DECOMPOSIÇÃO DO PREÇO (por unidade)
A17: Preço Total (4 sem, s/ desc.) | B17: =B16*B4 -> 9769.4211 | D17: Componente | E17: R$/un. | F17: % do Preço
A18: DESCONTOS | D18: Custo GPC | E18: =B9 -> 0.2998 | F18: =E18/B25 -> 0.181476
A19: Desc. por Prazo | B19: =IF(D4=4,0,INDEX(Premissas!B9:B20,MATCH(D4,{8,12,16,20,24,28,32,36,40,44,48,52},0))) -> 0.11 | D19: Frete/un. | E19: =B11/B4 -> 0.071438 | F19: =E19/B25 -> 0.043243103
A20: Desc. por Quantidade | B20: =1-(B16/Descontos!B$28) -> 0.25808785 | D20: IRPJ | E20: =B25*B28 -> 0.099120546 | F20: =B28 -> 0.06
A21: Desc. Forma Pagamento | B21: =IF(F4="Pix",Premissas!B22,IF(F4="Boleto",Premissas!B23,IF(F4="Cartão",-Premissas!B24,0))) -> 0.05 | D21: Com. Restaurante | E21: =B25*B30 -> 0.24780136 | F21: =B30 -> 0.15
A22: Desc. Combinado (vs base 1k/4sem) | B22: =1-((1-B19)*(1-B20)*(1-B21)) -> 0.37271328 | D22: Com. Comercial | E22: =B25*B32 -> 0.16520091 | F22: =B32 -> 0.1
A23: Nº Períodos (x4 sem) | B23: =D4/4 -> 6 | D23: Margem / Lucro | E23: =B25-E18-E19-E20-E21-E22 -> 0.76864828 | F23: =1-F18-F19-F20-F21-F22 -> 0.4652809
A24: Preço Total c/ Descontos | B24: =B17*B23*(1-B19)*(1-B21) -> 49560.273 | D24: Preço Unit. c/ Desc. | E24: =B25 -> 1.6520091 | F24: 1
A25: Preço Unit. c/ Descontos | B25: =B16*(1-B19)*(1-B21) -> 1.6520091
A27: COMISSÕES E IMPOSTOS
A28: IRPJ | B28: =Premissas!B4 -> 0.06
A29: Valor IRPJ | B29: =B24*B28 -> 2973.6164
A30: Comissão Restaurante (%) | B30: =Premissas!B5 -> 0.15
A31: Valor Comissão Restaurante | B31: =B24*B30 -> 7434.0409
A32: Comissão Comercial (%) | B32: =Premissas!B6 -> 0.1
A33: Valor Comissão Comercial | B33: =B24*B32 -> 4956.0273
A34: Total Deduções | B34: =B29+B31+B33 -> 15363.685
A35: RESULTADO FINAL
A36: Receita Líquida (após deduções) | B36: =B24-B34 -> 34196.588
A37: Lucro Bruto (Rec.Líq. - Custo Total) | B37: =B36-(B12*B23) -> 23059.448
A38: Margem Líquida (após deduções) | B38: =B37/B24 -> 0.4652809
A39: Margem sobre Receita Total | B39: =B14 -> 0.5
A40: Lucro por Unidade | B40: =B37/(B4*B23) -> 0.76864828
A41: Custo por Unidade (total) | B41: =B12/B4 -> 0.371238

Sheet Premissas
A1: PREMISSAS VEXA
A3: IMPOSTOS E COMISSÕES
A4: IRPJ | B4: 0.06
A5: Comissão Restaurante | B5: 0.15
A6: Comissão Comercial | B6: 0.1
A8: DESCONTOS POR PRAZO
A9: Desc. 8 semanas | B9: 0.03
A10: Desc. 12 semanas | B10: 0.05
A11: Desc. 16 semanas | B11: 0.07
A12: Desc. 20 semanas | B12: 0.09
A13: Desc. 24 semanas | B13: 0.11
A14: Desc. 28 semanas | B14: 0.13
A15: Desc. 32 semanas | B15: 0.15
A16: Desc. 36 semanas | B16: 0.17
A17: Desc. 40 semanas | B17: 0.19
A18: Desc. 44 semanas | B18: 0.21
A19: Desc. 48 semanas | B19: 0.23
A20: Desc. 52 semanas | B20: 0.25
A21: FORMA DE PAGAMENTO
A22: Desc. Pix | B22: 0.05
A23: Desc. Boleto | B23: 0
A24: Acrésc. Cartão | B24: 0
A26: DESCONTOS POR QUANTIDADE
A27: 5.000 - 9.999 un.
A28: 10.000 - 14.999 un.
A29: 15.000 - 19.999 un.
A30: 20.000+ un.
A32: CUSTOS POR FAIXA DE VOLUME
A33: Volume | B33: Custo GPC Unit. (R$) | C33: Margem Alvo | D33: Frete (R$) | E33: Artes
A34: 1000 | B34: 0.419 | C34: 0.5 | D34: 80.38 | E34: 1
A35: 2000 | B35: 0.3495 | C35: 0.5 | D35: 138.16 | E35: 1
A36: 3000 | B36: 0.333 | C36: 0.5 | D36: 219.03 | E36: 1
A37: 4000 | B37: 0.3248 | C37: 0.5 | D37: 299.41 | E37: 1
A38: 5000 | B38: 0.2998 | C38: 0.5 | D38: 357.19 | E38: 1
A39: 6000 | B39: 0.2998 | C39: 0.5 | D39: 438.06 | E39: 1
A40: 7000 | B40: 0.2998 | C40: 0.5 | D40: 518.44 | E40: 1
A41: 8000 | B41: 0.2998 | C41: 0.5 | D41: 576.22 | E41: 1
A42: 9000 | B42: 0.2998 | C42: 0.5 | D42: 657.09 | E42: 1
A43: 10000 | B43: 0.27 | C43: 0.5 | D43: 737.47 | E43: 1
A44: 11000 | B44: 0.27 | C44: 0.5 | D44: 876.12 | E44: 1
A45: 12000 | B45: 0.27 | C45: 0.5 | D45: 956.5 | E45: 1
... A53: 20000 | B53: 0.26 | C53: 0.5 | D53: 1613.59 | E53: 1

Sheet Descontos
A1: TABELA DE DESCONTOS VEXA
A3: DESCONTO POR PRAZO (% sobre preço base 4 semanas)
A4: Volume | B4: Preço Base (4 sem) | C4: 8 sem (-5.0%) | D4: 12 sem (-8.0%) | E4: 16 sem (-10.0%) | F4: 20 sem (-9.0%) | G4: 24 sem (-11.0%) | H4: 28 sem (-13.0%) | I4: 32 sem (-15.0%) | J4: 36 sem (-17.0%) | K4: 40 sem (-19.0%) | L4: 44 sem (-21.0%) | M4: 48 sem (-23.0%) | N4: 52 sem (-25.0%) | Q4: Desc. Máx. Combo
A5: 1000 | B5: =(Premissas!B34*Premissas!A34+Premissas!D34+Premissas!E34)/(1-Premissas!C34-Premissas!$B$4-Premissas!$B$5-Premissas!$B$6) -> 2633.5789 | C5: =B5*2*(1-Premissas!$B$9) -> 5109.1432 | D5: =B5*3*(1-Premissas!$B$10) -> 7505.7 | E5: =B5*4*(1-Premissas!$B$11) -> 9796.9137 | F5: =B5*5*(1-Premissas!$B$12) -> 11982.784 | G5: =B5*6*(1-Premissas!$B$13) -> 14063.312 | H5: =B5*7*(1-Premissas!$B$14) -> 16038.496 | I5: =B5*8*(1-Premissas!$B$15) -> 17908.337 | J5: =B5*9*(1-Premissas!$B$16) -> 19672.835 | K5: =B5*10*(1-Premissas!$B$17) -> 21331.989 | L5: =B5*11*(1-Premissas!$B$18) -> 22885.801 | M5: =B5*12*(1-Premissas!$B$19) -> 24334.269 | N5: =B5*13*(1-Premissas!$B$20) -> 25677.395 | Q5: =1-(N5/(B5*13)) -> 0.25
A6: 2000 | B6: =(Premissas!B35*Premissas!A35+Premissas!D35+Premissas!E35)/(1-Premissas!C35-Premissas!$B$4-Premissas!$B$5-Premissas!$B$6) -> 4411.3684 | C6: =B6*2*(1-Premissas!$B$9) -> 8558.0547 | D6: =B6*3*(1-Premissas!$B$10) -> 12572.4 | E6: =B6*4*(1-Premissas!$B$11) -> 16410.291 | F6: =B6*5*(1-Premissas!$B$12) -> 20071.726 | G6: =B6*6*(1-Premissas!$B$13) -> 23556.707 | H6: =B6*7*(1-Premissas!$B$14) -> 26865.234 | I6: =B6*8*(1-Premissas!$B$15) -> 29997.305 | J6: =B6*9*(1-Premissas!$B$16) -> 32952.922 | K6: =B6*10*(1-Premissas!$B$17) -> 35732.084 | L6: =B6*11*(1-Premissas!$B$18) -> 38334.792 | M6: =B6*12*(1-Premissas!$B$19) -> 40761.044 | N6: =B6*13*(1-Premissas!$B$20) -> 43010.842 | Q6: =1-(N6/(B6*13)) -> 0.25
A7: 3000 | B7: =(Premissas!B36*Premissas!A36+Premissas!D36+Premissas!E36)/(1-Premissas!C36-Premissas!$B$4-Premissas!$B$5-Premissas!$B$6) -> 6415.9474 | C7: =B7*2*(1-Premissas!$B$9) -> 12446.938 | D7: =B7*3*(1-Premissas!$B$10) -> 18285.45 | E7: =B7*4*(1-Premissas!$B$11) -> 23867.324 | F7: =B7*5*(1-Premissas!$B$12) -> 29192.561 | G7: =B7*6*(1-Premissas!$B$13) -> 34261.159 | H7: =B7*7*(1-Premissas!$B$14) -> 39073.119 | I7: =B7*8*(1-Premissas!$B$15) -> 43628.442 | J7: =B7*9*(1-Premissas!$B$16) -> 47927.127 | K7: =B7*10*(1-Premissas!$B$17) -> 51969.174 | L7: =B7*11*(1-Premissas!$B$18) -> 55754.583 | M7: =B7*12*(1-Premissas!$B$19) -> 59283.354 | N7: =B7*13*(1-Premissas!$B$20) -> 62555.487 | Q7: =1-(N7/(B7*13)) -> 0.25
A8: 4000 | B8: =(Premissas!B37*Premissas!A37+Premissas!D37+Premissas!E37)/(1-Premissas!C37-Premissas!$B$4-Premissas!$B$5-Premissas!$B$6) -> 8419 | C8: =B8*2*(1-Premissas!$B$9) -> 16332.86 | D8: =B8*3*(1-Premissas!$B$10) -> 23994.15 | E8: =B8*4*(1-Premissas!$B$11) -> 31318.68 | F8: =B8*5*(1-Premissas!$B$12) -> 38306.45 | G8: =B8*6*(1-Premissas!$B$13) -> 44957.46 | H8: =B8*7*(1-Premissas!$B$14) -> 51271.71 | I8: =B8*8*(1-Premissas!$B$15) -> 57249.2 | J8: =B8*9*(1-Premissas!$B$16) -> 62889.93 | K8: =B8*10*(1-Premissas!$B$17) -> 68193.9 | L8: =B8*11*(1-Premissas!$B$18) -> 73161.11 | M8: =B8*12*(1-Premissas!$B$19) -> 77791.56 | N8: =B8*13*(1-Premissas!$B$20) -> 82085.25 | Q8: =1-(N8/(B8*13)) -> 0.25
A9: 5000 | B9: =(Premissas!B38*Premissas!A38+Premissas!D38+Premissas!E38)/(1-Premissas!C38-Premissas!$B$4-Premissas!$B$5-Premissas!$B$6) -> 9774.6842 | C9: =B9*2*(1-Premissas!$B$9) -> 18962.887 | D9: =B9*3*(1-Premissas!$B$10) -> 27857.85 | E9: =B9*4*(1-Premissas!$B$11) -> 36361.825 | F9: =B9*5*(1-Premissas!$B$12) -> 44474.813 | G9: =B9*6*(1-Premissas!$B$13) -> 52196.814 | H9: =B9*7*(1-Premissas!$B$14) -> 59527.827 | I9: =B9*8*(1-Premissas!$B$15) -> 66467.853 | J9: =B9*9*(1-Premissas!$B$16) -> 73016.891 | K9: =B9*10*(1-Premissas!$B$17) -> 79174.942 | L9: =B9*11*(1-Premissas!$B$18) -> 84942.006 | M9: =B9*12*(1-Premissas!$B$19) -> 90318.082 | N9: =B9*13*(1-Premissas!$B$20) -> 95303.171 | Q9: =1-(N9/(B9*13)) -> 0.25
A10: 6000 | B10: =(Premissas!B39*Premissas!A39+Premissas!D39+Premissas!E39)/(1-Premissas!C39-Premissas!$B$4-Premissas!$B$5-Premissas!$B$6) -> 11778.211 | C10: =B10*2*(1-Premissas!$B$9) -> 22849.728 | D10: =B10*3*(1-Premissas!$B$10) -> 33567.9 | E10: =B10*4*(1-Premissas!$B$11) -> 43814.943 | F10: =B10*5*(1-Premissas!$B$12) -> 53590.858 | G10: =B10*6*(1-Premissas!$B$13) -> 62895.644 | H10: =B10*7*(1-Premissas!$B$14) -> 71729.302 | I10: =B10*8*(1-Premissas!$B$15) -> 80091.832 | J10: =B10*9*(1-Premissas!$B$16) -> 87983.233 | K10: =B10*10*(1-Premissas!$B$17) -> 95403.505 | L10: =B10*11*(1-Premissas!$B$18) -> 102352.65 | M10: =B10*12*(1-Premissas!$B$19) -> 108830.67 | N10: =B10*13*(1-Premissas!$B$20) -> 114837.55 | Q10: =1-(N10/(B10*13)) -> 0.25
A11: 7000 | B11: =(Premissas!B40*Premissas!A40+Premissas!D40+Premissas!E40)/(1-Premissas!C40-Premissas!$B$4-Premissas!$B$5-Premissas!$B$6) -> 13779.158 | C11: =B11*2*(1-Premissas!$B$9) -> 26731.566 | D11: =B11*3*(1-Premissas!$B$10) -> 39270.6 | E11: =B11*4*(1-Premissas!$B$11) -> 51258.467 | F11: =B11*5*(1-Premissas!$B$12) -> 62695.168 | G11: =B11*6*(1-Premissas!$B$13) -> 73580.703 | H11: =B11*7*(1-Premissas!$B$14) -> 83915.072 | I11: =B11*8*(1-Premissas!$B$15) -> 93698.274 | J11: =B11*9*(1-Premissas!$B$16) -> 102930.31 | K11: =B11*10*(1-Premissas!$B$17) -> 111611.18 | L11: =B11*11*(1-Premissas!$B$18) -> 119740.88 | M11: =B11*12*(1-Premissas!$B$19) -> 127319.42 | N11: =B11*13*(1-Premissas!$B$20) -> 134346.79 | Q11: =1-(N11/(B11*13)) -> 0.25
A12: 8000 | B12: =(Premissas!B41*Premissas!A41+Premissas!D41+Premissas!E41)/(1-Premissas!C41-Premissas!$B$4-Premissas!$B$5-Premissas!$B$6) -> 15661.158 | C12: =B12*2*(1-Premissas!$B$9) -> 30382.646 | D12: =B12*3*(1-Premissas!$B$10) -> 44634.3 | E12: =B12*4*(1-Premissas!$B$11) -> 58259.507 | F12: =B12*5*(1-Premissas!$B$12) -> 71258.268 | G12: =B12*6*(1-Premissas!$B$13) -> 83630.583 | H12: =B12*7*(1-Premissas!$B$14) -> 95376.452 | I12: =B12*8*(1-Premissas!$B$15) -> 106495.87 | J12: =B12*9*(1-Premissas!$B$16) -> 116988.85 | K12: =B12*10*(1-Premissas!$B$17) -> 126855.38 | L12: =B12*11*(1-Premissas!$B$18) -> 136095.46 | M12: =B12*12*(1-Premissas!$B$19) -> 144709.1 | N12: =B12*13*(1-Premissas!$B$20) -> 152696.29 | Q12: =1-(N12/(B12*13)) -> 0.25
A13: 9000 | B13: =(Premissas!B42*Premissas!A42+Premissas!D42+Premissas!E42)/(1-Premissas!C42-Premissas!$B$4-Premissas!$B$5-Premissas!$B$6) -> 17664.684 | C13: =B13*2*(1-Premissas!$B$9) -> 34269.487 | D13: =B13*3*(1-Premissas!$B$10) -> 50344.35 | E13: =B13*4*(1-Premissas!$B$11) -> 65712.625 | F13: =B13*5*(1-Premissas!$B$12) -> 80374.313 | G13: =B13*6*(1-Premissas!$B$13) -> 94329.414 | H13: =B13*7*(1-Premissas!$B$14) -> 107577.93 | I13: =B13*8*(1-Premissas!$B$15) -> 120119.85 | J13: =B13*9*(1-Premissas!$B$16) -> 131955.19 | K13: =B13*10*(1-Premissas!$B$17) -> 143083.94 | L13: =B13*11*(1-Premissas!$B$18) -> 153506.11 | M13: =B13*12*(1-Premissas!$B$19) -> 163221.68 | N13: =B13*13*(1-Premissas!$B$20) -> 172230.67 | Q13: =1-(N13/(B13*13)) -> 0.25
A14: 10000 | B14: =(Premissas!B43*Premissas!A43+Premissas!D43+Premissas!E43)/(1-Premissas!C43-Premissas!$B$4-Premissas!$B$5-Premissas!$B$6) -> 18097.211 | C14: =B14*2*(1-Premissas!$B$9) -> 35108.588 | D14: =B14*3*(1-Premissas!$B$10) -> 51577.05 | E14: =B14*4*(1-Premissas!$B$11) -> 67321.623 | F14: =B14*5*(1-Premissas!$B$12) -> 82342.308 | G14: =B14*6*(1-Premissas!$B$13) -> 96639.104 | H14: =B14*7*(1-Premissas!$B$14) -> 110212.01 | I14: =B14*8*(1-Premissas!$B$15) -> 123061.03 | J14: =B14*9*(1-Premissas!$B$16) -> 135186.16 | K14: =B14*10*(1-Premissas!$B$17) -> 146587.41 | L14: =B14*11*(1-Premissas!$B$18) -> 157264.76 | M14: =B14*12*(1-Premissas!$B$19) -> 167218.23 | N14: =B14*13*(1-Premissas!$B$20) -> 176447.8 | Q14: =1-(N14/(B14*13)) -> 0.25
A15: 11000 | B15: =(Premissas!B44*Premissas!A44+Premissas!D44+Premissas!E44)/(1-Premissas!C44-Premissas!$B$4-Premissas!$B$5-Premissas!$B$6) -> 20248 | C15: =B15*2*(1-Premissas!$B$9) -> 39281.12 | D15: =B15*3*(1-Premissas!$B$10) -> 57706.8 | E15: =B15*4*(1-Premissas!$B$11) -> 75322.56 | F15: =B15*5*(1-Premissas!$B$12) -> 92128.4 | G15: =B15*6*(1-Premissas!$B$13) -> 108124.32 | H15: =B15*7*(1-Premissas!$B$14) -> 123310.32 | I15: =B15*8*(1-Premissas!$B$15) -> 137686.4 | J15: =B15*9*(1-Premissas!$B$16) -> 151252.56 | K15: =B15*10*(1-Premissas!$B$17) -> 164008.8 | L15: =B15*11*(1-Premissas!$B$18) -> 175955.12 | M15: =B15*12*(1-Premissas!$B$19) -> 187091.52 | N15: =B15*13*(1-Premissas!$B$20) -> 197418 | Q15: =1-(N15/(B15*13)) -> 0.25
A16: 12000 | B16: =(Premissas!B45*Premissas!A45+Premissas!D45+Premissas!E45)/(1-Premissas!C45-Premissas!$B$4-Premissas!$B$5-Premissas!$B$6) -> 22092.105 | C16: =B16*2*(1-Premissas!$B$9) -> 42858.684 | D16: =B16*3*(1-Premissas!$B$10) -> 62962.5 | E16: =B16*4*(1-Premissas!$B$11) -> 82182.632 | F16: =B16*5*(1-Premissas!$B$12) -> 100519.08 | G16: =B16*6*(1-Premissas!$B$13) -> 117971.84 | H16: =B16*7*(1-Premissas!$B$14) -> 134540.92 | I16: =B16*8*(1-Premissas!$B$15) -> 150226.32 | J16: =B16*9*(1-Premissas!$B$16) -> 165028.03 | K16: =B16*10*(1-Premissas!$B$17) -> 178946.05 | L16: =B16*11*(1-Premissas!$B$18) -> 191980.39 | M16: =B16*12*(1-Premissas!$B$19) -> 204131.05 | N16: =B16*13*(1-Premissas!$B$20) -> 215398.03 | Q16: =1-(N16/(B16*13)) -> 0.25
... A24: 20000 | B24: =(Premissas!B53*Premissas!A53+Premissas!D53+Premissas!E53)/(1-Premissas!C53-Premissas!$B$4-Premissas!$B$5-Premissas!$B$6) -> 35866.263 | C24: =B24*2*(1-Premissas!$B$9) -> 69580.551 | D24: =B24*3*(1-Premissas!$B$10) -> 102218.85 | E24: =B24*4*(1-Premissas!$B$11) -> 133422.5 | F24: =B24*5*(1-Premissas!$B$12) -> 163191.5 | G24: =B24*6*(1-Premissas!$B$13) -> 191525.85 | H24: =B24*7*(1-Premissas!$B$14) -> 218425.54 | I24: =B24*8*(1-Premissas!$B$15) -> 243890.59 | J24: =B24*9*(1-Premissas!$B$16) -> 267920.99 | K24: =B24*10*(1-Premissas!$B$17) -> 290516.73 | L24: =B24*11*(1-Premissas!$B$18) -> 311677.83 | M24: =B24*12*(1-Premissas!$B$19) -> 331404.27 | N24: =B24*13*(1-Premissas!$B$20) -> 349696.07 | Q24: =1-(N24/(B24*13)) -> 0.25
A26: DESCONTO POR QUANTIDADE (% sobre preço unitário)
A27: Volume | B27: Preço Unit. Original | C27: Unit. 4 sem | D27: Unit. 8 sem | E27: Unit. 12 sem | F27: Unit. 16 sem | G27: Unit. 20 sem | H27: Unit. 24 sem | I27: Unit. 28 sem | J27: Unit. 32 sem | K27: Unit. 36 sem | L27: Unit. 40 sem | M27: Unit. 44 sem | N27: Unit. 48 sem | O27: Unit. 52 sem | P27: Economia Total (R$) | Q27: % Desconto Nominal Qtd.
A28: =Premissas!A34 -> 1000 | B28: =(Premissas!B34+Premissas!D34/Premissas!A34+Premissas!E34/Premissas!A34)/(1-Premissas!C34-Premissas!$B$4-Premissas!$B$5-Premissas!$B$6) -> 2.6335789 | C28: =B28 -> 2.6335789 | D28: =B28*(1-Premissas!$B$9) -> 2.5545716 | E28: =B28*(1-Premissas!$B$10) -> 2.5019 | F28: =B28*(1-Premissas!$B$11) -> 2.4492284 | G28: =B28*(1-Premissas!$B$12) -> 2.3965568 | H28: =B28*(1-Premissas!$B$13) -> 2.3438853 | I28: =B28*(1-Premissas!$B$14) -> 2.2912137 | J28: =B28*(1-Premissas!$B$15) -> 2.2385421 | K28: =B28*(1-Premissas!$B$16) -> 2.1858705 | L28: =B28*(1-Premissas!$B$17) -> 2.1331989 | M28: =B28*(1-Premissas!$B$18) -> 2.0805274 | N28: =B28*(1-Premissas!$B$19) -> 2.0278558 | O28: =B28*(1-Premissas!$B$20) -> 1.9751842 | P28: =(B28-O28)*A28 -> 658.39474 | Q28: =1-(B28/B$28) -> 0
A29: =Premissas!A35 -> 2000 | B29: =(Premissas!B35+Premissas!D35/Premissas!A35+Premissas!E35/Premissas!A35)/(1-Premissas!C35-Premissas!$B$4-Premissas!$B$5-Premissas!$B$6) -> 2.2056842 | C29: =B29 -> 2.2056842 | D29: =B29*(1-Premissas!$B$9) -> 2.1395137 | E29: =B29*(1-Premissas!$B$10) -> 2.0954 | F29: =B29*(1-Premissas!$B$11) -> 2.0512863 | G29: =B29*(1-Premissas!$B$12) -> 2.0071726 | H29: =B29*(1-Premissas!$B$13) -> 1.9630589 | I29: =B29*(1-Premissas!$B$14) -> 1.9189453 | J29: =B29*(1-Premissas!$B$15) -> 1.8748316 | K29: =B29*(1-Premissas!$B$16) -> 1.8307179 | L29: =B29*(1-Premissas!$B$17) -> 1.7866042 | M29: =B29*(1-Premissas!$B$18) -> 1.7424905 | N29: =B29*(1-Premissas!$B$19) -> 1.6983768 | O29: =B29*(1-Premissas!$B$20) -> 1.6542632 | P29: =(B29-O29)*A29 -> 1102.8421 | Q29: =1-(B29/B$28) -> 0.16247652
A30: =Premissas!A36 -> 3000 | B30: =(Premissas!B36+Premissas!D36/Premissas!A36+Premissas!E36/Premissas!A36)/(1-Premissas!C36-Premissas!$B$4-Premissas!$B$5-Premissas!$B$6) -> 2.1386491 | C30: =B30 -> 2.1386491 | D30: =B30*(1-Premissas!$B$9) -> 2.0744896 | E30: =B30*(1-Premissas!$B$10) -> 2.0317167 | F30: =B30*(1-Premissas!$B$11) -> 1.9889437 | G30: =B30*(1-Premissas!$B$12) -> 1.9461707 | H30: =B30*(1-Premissas!$B$13) -> 1.9033977 | I30: =B30*(1-Premissas!$B$14) -> 1.8606247 | J30: =B30*(1-Premissas!$B$15) -> 1.8178518 | K30: =B30*(1-Premissas!$B$16) -> 1.7750788 | L30: =B30*(1-Premissas!$B$17) -> 1.7323058 | M30: =B30*(1-Premissas!$B$18) -> 1.6895328 | N30: =B30*(1-Premissas!$B$19) -> 1.6467598 | O30: =B30*(1-Premissas!$B$20) -> 1.6039868 | P30: =(B30-O30)*A30 -> 1603.9868 | Q30: =1-(B30/B$28) -> 0.18793051
A31: =Premissas!A37 -> 4000 | B31: =(Premissas!B37+Premissas!D37/Premissas!A37+Premissas!E37/Premissas!A37)/(1-Premissas!C37-Premissas!$B$4-Premissas!$B$5-Premissas!$B$6) -> 2.10475 | C31: =B31 -> 2.10475 | D31: =B31*(1-Premissas!$B$9) -> 2.0416075 | E31: =B31*(1-Premissas!$B$10) -> 1.9995125 | F31: =B31*(1-Premissas!$B$11) -> 1.9574175 | G31: =B31*(1-Premissas!$B$12) -> 1.9153225 | H31: =B31*(1-Premissas!$B$13) -> 1.8732275 | I31: =B31*(1-Premissas!$B$14) -> 1.8311325 | J31: =B31*(1-Premissas!$B$15) -> 1.7890375 | K31: =B31*(1-Premissas!$B$16) -> 1.7469425 | L31: =B31*(1-Premissas!$B$17) -> 1.7048475 | M31: =B31*(1-Premissas!$B$18) -> 1.6627525 | N31: =B31*(1-Premissas!$B$19) -> 1.6206575 | O31: =B31*(1-Premissas!$B$20) -> 1.5785625 | P31: =(B31-O31)*A31 -> 2104.75 | Q31: =1-(B31/B$28) -> 0.20080239
A32: =Premissas!A38 -> 5000 | B32: =(Premissas!B38+Premissas!D38/Premissas!A38+Premissas!E38/Premissas!A38)/(1-Premissas!C38-Premissas!$B$4-Premissas!$B$5-Premissas!$B$6) -> 1.9549368 | C32: =B32 -> 1.9549368 | D32: =B32*(1-Premissas!$B$9) -> 1.8962887 | E32: =B32*(1-Premissas!$B$10) -> 1.85719 | F32: =B32*(1-Premissas!$B$11) -> 1.8180913 | G32: =B32*(1-Premissas!$B$12) -> 1.7789925 | H32: =B32*(1-Premissas!$B$13) -> 1.7398938 | I32: =B32*(1-Premissas!$B$14) -> 1.7007951 | J32: =B32*(1-Premissas!$B$15) -> 1.6616963 | K32: =B32*(1-Premissas!$B$16) -> 1.6225976 | L32: =B32*(1-Premissas!$B$17) -> 1.5834988 | M32: =B32*(1-Premissas!$B$18) -> 1.5444001 | N32: =B32*(1-Premissas!$B$19) -> 1.5053014 | O32: =B32*(1-Premissas!$B$20) -> 1.4662026 | P32: =(B32-O32)*A32 -> 2443.6711 | Q32: =1-(B32/B$28) -> 0.25768816
A33: =Premissas!A39 -> 6000 | B33: =(Premissas!B39+Premissas!D39/Premissas!A39+Premissas!E39/Premissas!A39)/(1-Premissas!C39-Premissas!$B$4-Premissas!$B$5-Premissas!$B$6) -> 1.9630351 | C33: =B33 -> 1.9630351 | D33: =B33*(1-Premissas!$B$9) -> 1.904144 | E33: =B33*(1-Premissas!$B$10) -> 1.8648833 | F33: =B33*(1-Premissas!$B$11) -> 1.8256226 | G33: =B33*(1-Premissas!$B$12) -> 1.7863619 | H33: =B33*(1-Premissas!$B$13) -> 1.7471012 | I33: =B33*(1-Premissas!$B$14) -> 1.7078405 | J33: =B33*(1-Premissas!$B$15) -> 1.6685798 | K33: =B33*(1-Premissas!$B$16) -> 1.6293191 | L33: =B33*(1-Premissas!$B$17) -> 1.5900584 | M33: =B33*(1-Premissas!$B$18) -> 1.5507977 | N33: =B33*(1-Premissas!$B$19) -> 1.511537 | O33: =B33*(1-Premissas!$B$20) -> 1.4722763 | P33: =(B33-O33)*A33 -> 2944.5526 | Q33: =1-(B33/B$28) -> 0.25461316
A34: =Premissas!A40 -> 7000 | B34: =(Premissas!B40+Premissas!D40/Premissas!A40+Premissas!E40/Premissas!A40)/(1-Premissas!C40-Premissas!$B$4-Premissas!$B$5-Premissas!$B$6) -> 1.9684511 | C34: =B34 -> 1.9684511 | D34: =B34*(1-Premissas!$B$9) -> 1.9093976 | E34: =B34*(1-Premissas!$B$10) -> 1.8700286 | F34: =B34*(1-Premissas!$B$11) -> 1.8306595 | G34: =B34*(1-Premissas!$B$12) -> 1.7912905 | H34: =B34*(1-Premissas!$B$13) -> 1.7519215 | I34: =B34*(1-Premissas!$B$14) -> 1.7125525 | J34: =B34*(1-Premissas!$B$15) -> 1.6731835 | K34: =B34*(1-Premissas!$B$16) -> 1.6338144 | L34: =B34*(1-Premissas!$B$17) -> 1.5944454 | M34: =B34*(1-Premissas!$B$18) -> 1.5550764 | N34: =B34*(1-Premissas!$B$19) -> 1.5157074 | O34: =B34*(1-Premissas!$B$20) -> 1.4763383 | P34: =(B34-O34)*A34 -> 3444.7895 | Q34: =1-(B34/B$28) -> 0.25255663
A35: =Premissas!A41 -> 8000 | B35: =(Premissas!B41+Premissas!D41/Premissas!A41+Premissas!E41/Premissas!A41)/(1-Premissas!C41-Premissas!$B$4-Premissas!$B$5-Premissas!$B$6) -> 1.9576447 | C35: =B35 -> 1.9576447 | D35: =B35*(1-Premissas!$B$9) -> 1.8989154 | E35: =B35*(1-Premissas!$B$10) -> 1.8597625 | F35: =B35*(1-Premissas!$B$11) -> 1.8206096 | G35: =B35*(1-Premissas!$B$12) -> 1.7814567 | H35: =B35*(1-Premissas!$B$13) -> 1.7423038 | I35: =B35*(1-Premissas!$B$14) -> 1.7031509 | J35: =B35*(1-Premissas!$B$15) -> 1.663998 | K35: =B35*(1-Premissas!$B$16) -> 1.6248451 | L35: =B35*(1-Premissas!$B$17) -> 1.5856922 | M35: =B35*(1-Premissas!$B$18) -> 1.5465393 | N35: =B35*(1-Premissas!$B$19) -> 1.5073864 | O35: =B35*(1-Premissas!$B$20) -> 1.4682336 | P35: =(B35-O35)*A35 -> 3915.2895 | Q35: =1-(B35/B$28) -> 0.25665994
A36: =Premissas!A42 -> 9000 | B36: =(Premissas!B42+Premissas!D42/Premissas!A42+Premissas!E42/Premissas!A42)/(1-Premissas!C42-Premissas!$B$4-Premissas!$B$5-Premissas!$B$6) -> 1.9627427 | C36: =B36 -> 1.9627427 | D36: =B36*(1-Premissas!$B$9) -> 1.9038604 | E36: =B36*(1-Premissas!$B$10) -> 1.8646056 | F36: =B36*(1-Premissas!$B$11) -> 1.8253507 | G36: =B36*(1-Premissas!$B$12) -> 1.7860958 | H36: =B36*(1-Premissas!$B$13) -> 1.746841 | I36: =B36*(1-Premissas!$B$14) -> 1.7075861 | J36: =B36*(1-Premissas!$B$15) -> 1.6683313 | K36: =B36*(1-Premissas!$B$16) -> 1.6290764 | L36: =B36*(1-Premissas!$B$17) -> 1.5898216 | M36: =B36*(1-Premissas!$B$18) -> 1.5505667 | N36: =B36*(1-Premissas!$B$19) -> 1.5113119 | O36: =B36*(1-Premissas!$B$20) -> 1.472057 | P36: =(B36-O36)*A36 -> 4416.1711 | Q36: =1-(B36/B$28) -> 0.25472419
A37: =Premissas!A43 -> 10000 | B37: =(Premissas!B43+Premissas!D43/Premissas!A43+Premissas!E43/Premissas!A43)/(1-Premissas!C43-Premissas!$B$4-Premissas!$B$5-Premissas!$B$6) -> 1.8097211 | C37: =B37 -> 1.8097211 | D37: =B37*(1-Premissas!$B$9) -> 1.7554294 | E37: =B37*(1-Premissas!$B$10) -> 1.719235 | F37: =B37*(1-Premissas!$B$11) -> 1.6830406 | G37: =B37*(1-Premissas!$B$12) -> 1.6468462 | H37: =B37*(1-Premissas!$B$13) -> 1.6106517 | I37: =B37*(1-Premissas!$B$14) -> 1.5744573 | J37: =B37*(1-Premissas!$B$15) -> 1.5382629 | K37: =B37*(1-Premissas!$B$16) -> 1.5020685 | L37: =B37*(1-Premissas!$B$17) -> 1.4658741 | M37: =B37*(1-Premissas!$B$18) -> 1.4296796 | N37: =B37*(1-Premissas!$B$19) -> 1.3934852 | O37: =B37*(1-Premissas!$B$20) -> 1.3572908 | P37: =(B37-O37)*A37 -> 4524.3026 | Q37: =1-(B37/B$28) -> 0.31282825
A38: =Premissas!A44 -> 11000 | B38: =(Premissas!B44+Premissas!D44/Premissas!A44+Premissas!E44/Premissas!A44)/(1-Premissas!C44-Premissas!$B$4-Premissas!$B$5-Premissas!$B$6) -> 1.8407273 | C38: =B38 -> 1.8407273 | D38: =B38*(1-Premissas!$B$9) -> 1.7855055 | E38: =B38*(1-Premissas!$B$10) -> 1.7486909 | F38: =B38*(1-Premissas!$B$11) -> 1.7118764 | G38: =B38*(1-Premissas!$B$12) -> 1.6750618 | H38: =B38*(1-Premissas!$B$13) -> 1.6382473 | I38: =B38*(1-Premissas!$B$14) -> 1.6014327 | J38: =B38*(1-Premissas!$B$15) -> 1.5646182 | K38: =B38*(1-Premissas!$B$16) -> 1.5278036 | L38: =B38*(1-Premissas!$B$17) -> 1.4909891 | M38: =B38*(1-Premissas!$B$18) -> 1.4541745 | N38: =B38*(1-Premissas!$B$19) -> 1.41736 | O38: =B38*(1-Premissas!$B$20) -> 1.3805455 | P38: =(B38-O38)*A38 -> 5062 | Q38: =1-(B38/B$28) -> 0.30105483
A39: =Premissas!A45 -> 12000 | B39: =(Premissas!B45+Premissas!D45/Premissas!A45+Premissas!E45/Premissas!A45)/(1-Premissas!C45-Premissas!$B$4-Premissas!$B$5-Premissas!$B$6) -> 1.8410088 | C39: =B39 -> 1.8410088 | D39: =B39*(1-Premissas!$B$9) -> 1.7857785 | E39: =B39*(1-Premissas!$B$10) -> 1.7489583 | F39: =B39*(1-Premissas!$B$11) -> 1.7121382 | G39: =B39*(1-Premissas!$B$12) -> 1.675318 | H39: =B39*(1-Premissas!$B$13) -> 1.6384978 | I39: =B39*(1-Premissas!$B$14) -> 1.6016776 | J39: =B39*(1-Premissas!$B$15) -> 1.5648575 | K39: =B39*(1-Premissas!$B$16) -> 1.5280373 | L39: =B39*(1-Premissas!$B$17) -> 1.4912171 | M39: =B39*(1-Premissas!$B$18) -> 1.4543969 | N39: =B39*(1-Premissas!$B$19) -> 1.4175768 | O39: =B39*(1-Premissas!$B$20) -> 1.3807566 | P39: =(B39-O39)*A39 -> 5523.0263 | Q39: =1-(B39/B$28) -> 0.30094795
... A47: =Premissas!A53 -> 20000 | B47: =(Premissas!B53+Premissas!D53/Premissas!A53+Premissas!E53/Premissas!A53)/(1-Premissas!C53-Premissas!$B$4-Premissas!$B$5-Premissas!$B$6) -> 1.7933132 | C47: =B47 -> 1.7933132 | D47: =B47*(1-Premissas!$B$9) -> 1.7395138 | E47: =B47*(1-Premissas!$B$10) -> 1.7036475 | F47: =B47*(1-Premissas!$B$11) -> 1.6677812 | G47: =B47*(1-Premissas!$B$12) -> 1.631915 | H47: =B47*(1-Premissas!$B$13) -> 1.5960487 | I47: =B47*(1-Premissas!$B$14) -> 1.5601824 | J47: =B47*(1-Premissas!$B$15) -> 1.5243162 | K47: =B47*(1-Premissas!$B$16) -> 1.4884499 | L47: =B47*(1-Premissas!$B$17) -> 1.4525837 | M47: =B47*(1-Premissas!$B$18) -> 1.4167174 | N47: =B47*(1-Premissas!$B$19) -> 1.3808511 | O47: =B47*(1-Premissas!$B$20) -> 1.3449849 | P47: =(B47-O47)*A47 -> 8966.5658 | Q47: =1-(B47/B$28) -> 0.31905852
A49: MATRIZ COMBINADA: Prazo × Quantidade (Preço Total com ambos descontos)
A50: Volume | B50: 4 semanas | C50: 8 semanas | D50: 12 semanas | E50: 16 semanas | F50: 20 semanas | G50: 24 semanas | H50: 28 semanas | I50: 32 semanas | J50: 36 semanas | K50: 40 semanas | L50: 44 semanas | M50: 48 semanas | N50: 52 semanas
A51: =Premissas!A34 -> 1000 | B51: =B5*(1-IF(A51>=20000,Premissas!$B$30,IF(A51>=15000,Premissas!$B$29,IF(A51>=10000,Premissas!$B$28,IF(A51>=5000,Premissas!$B$27,0))))) -> 2633.5789 | C51: =B5*2*(1-Premissas!$B$9)*(1-IF(A51>=20000,Premissas!$B$30,IF(A51>=15000,Premissas!$B$29,IF(A51>=10000,Premissas!$B$28,IF(A51>=5000,Premissas!$B$27,0))))) -> 5109.1432 | D51: =B5*3*(1-Premissas!$B$10)*(1-IF(A51>=20000,Premissas!$B$30,IF(A51>=15000,Premissas!$B$29,IF(A51>=10000,Premissas!$B$28,IF(A51>=5000,Premissas!$B$27,0))))) -> 7505.7 | E51: =B5*4*(1-Premissas!$B$11)*(1-IF(A51>=20000,Premissas!$B$30,IF(A51>=15000,Premissas!$B$29,IF(A51>=10000,Premissas!$B$28,IF(A51>=5000,Premissas!$B$27,0))))) -> 9796.9137 | F51: =B5*5*(1-Premissas!$B$12)*(1-IF(A51>=20000,Premissas!$B$30,IF(A51>=15000,Premissas!$B$29,IF(A51>=10000,Premissas!$B$28,IF(A51>=5000,Premissas!$B$27,0))))) -> 11982.784 | G51: =B5*6*(1-Premissas!$B$13)*(1-IF(A51>=20000,Premissas!$B$30,IF(A51>=15000,Premissas!$B$29,IF(A51>=10000,Premissas!$B$28,IF(A51>=5000,Premissas!$B$27,0))))) -> 14063.312 | H51: =B5*7*(1-Premissas!$B$14)*(1-IF(A51>=20000,Premissas!$B$30,IF(A51>=15000,Premissas!$B$29,IF(A51>=10000,Premissas!$B$28,IF(A51>=5000,Premissas!$B$27,0))))) -> 16038.496 | I51: =B5*8*(1-Premissas!$B$15)*(1-IF(A51>=20000,Premissas!$B$30,IF(A51>=15000,Premissas!$B$29,IF(A51>=10000,Premissas!$B$28,IF(A51>=5000,Premissas!$B$27,0))))) -> 17908.337 | J51: =B5*9*(1-Premissas!$B$16)*(1-IF(A51>=20000,Premissas!$B$30,IF(A51>=15000,Premissas!$B$29,IF(A51>=10000,Premissas!$B$28,IF(A51>=5000,Premissas!$B$27,0))))) -> 19672.835 | K51: =B5*10*(1-Premissas!$B$17)*(1-IF(A51>=20000,Premissas!$B$30,IF(A51>=15000,Premissas!$B$29,IF(A51>=10000,Premissas!$B$28,IF(A51>=5000,Premissas!$B$27,0))))) -> 21331.989 | L51: =B5*11*(1-Premissas!$B$18)*(1-IF(A51>=20000,Premissas!$B$30,IF(A51>=15000,Premissas!$B$29,IF(A51>=10000,Premissas!$B$28,IF(A51>=5000,Premissas!$B$27,0))))) -> 22885.801 | M51: =B5*12*(1-Premissas!$B$19)*(1-IF(A51>=20000,Premissas!$B$30,IF(A51>=15000,Premissas!$B$29,IF(A51>=10000,Premissas!$B$28,IF(A51>=5000,Premissas!$B$27,0))))) -> 24334.269 | N51: =B5*13*(1-Premissas!$B$20)*(1-IF(A51>=20000,Premissas!$B$30,IF(A51>=15000,Premissas!$B$29,IF(A51>=10000,Premissas!$B$28,IF(A51>=5000,Premissas!$B$27,0))))) -> 25677.395
A52: =Premissas!A35 -> 2000 | B52: =B6*(1-IF(A52>=20000,Premissas!$B$30,IF(A52>=15000,Premissas!$B$29,IF(A52>=10000,Premissas!$B$28,IF(A52>=5000,Premissas!$B$27,0))))) -> 4411.3684 | C52: =B6*2*(1-Premissas!$B$9)*(1-IF(A52>=20000,Premissas!$B$30,IF(A52>=15000,Premissas!$B$29,IF(A52>=10000,Premissas!$B$28,IF(A52>=5000,Premissas!$B$27,0))))) -> 8558.0547 | D52: =B6*3*(1-Premissas!$B$10)*(1-IF(A52>=20000,Premissas!$B$30,IF(A52>=15000,Premissas!$B$29,IF(A52>=10000,Premissas!$B$28,IF(A52>=5000,Premissas!$B$27,0))))) -> 12572.4 | E52: =B6*4*(1-Premissas!$B$11)*(1-IF(A52>=20000,Premissas!$B$30,IF(A52>=15000,Premissas!$B$29,IF(A52>=10000,Premissas!$B$28,IF(A52>=5000,Premissas!$B$27,0))))) -> 16410.291 | F52: =B6*5*(1-Premissas!$B$12)*(1-IF(A52>=20000,Premissas!$B$30,IF(A52>=15000,Premissas!$B$29,IF(A52>=10000,Premissas!$B$28,IF(A52>=5000,Premissas!$B$27,0))))) -> 20071.726 | G52: =B6*6*(1-Premissas!$B$13)*(1-IF(A52>=20000,Premissas!$B$30,IF(A52>=15000,Premissas!$B$29,IF(A52>=10000,Premissas!$B$28,IF(A52>=5000,Premissas!$B$27,0))))) -> 23556.707 | H52: =B6*7*(1-Premissas!$B$14)*(1-IF(A52>=20000,Premissas!$B$30,IF(A52>=15000,Premissas!$B$29,IF(A52>=10000,Premissas!$B$28,IF(A52>=5000,Premissas!$B$27,0))))) -> 26865.234 | I52: =B6*8*(1-Premissas!$B$15)*(1-IF(A52>=20000,Premissas!$B$30,IF(A52>=15000,Premissas!$B$29,IF(A52>=10000,Premissas!$B$28,IF(A52>=5000,Premissas!$B$27,0))))) -> 29997.305 | J52: =B6*9*(1-Premissas!$B$16)*(1-IF(A52>=20000,Premissas!$B$30,IF(A52>=15000,Premissas!$B$29,IF(A52>=10000,Premissas!$B$28,IF(A52>=5000,Premissas!$B$27,0))))) -> 32952.922 | K52: =B6*10*(1-Premissas!$B$17)*(1-IF(A52>=20000,Premissas!$B$30,IF(A52>=15000,Premissas!$B$29,IF(A52>=10000,Premissas!$B$28,IF(A52>=5000,Premissas!$B$27,0))))) -> 35732.084 | L52: =B6*11*(1-Premissas!$B$18)*(1-IF(A52>=20000,Premissas!$B$30,IF(A52>=15000,Premissas!$B$29,IF(A52>=10000,Premissas!$B$28,IF(A52>=5000,Premissas!$B$27,0))))) -> 38334.792 | M52: =B6*12*(1-Premissas!$B$19)*(1-IF(A52>=20000,Premissas!$B$30,IF(A52>=15000,Premissas!$B$29,IF(A52>=10000,Premissas!$B$28,IF(A52>=5000,Premissas!$B$27,0))))) -> 40761.044 | N52: =B6*13*(1-Premissas!$B$20)*(1-IF(A52>=20000,Premissas!$B$30,IF(A52>=15000,Premissas!$B$29,IF(A52>=10000,Premissas!$B$28,IF(A52>=5000,Premissas!$B$27,0))))) -> 43010.842
A53: =Premissas!A36 -> 3000 | B53: =B7*(1-IF(A53>=20000,Premissas!$B$30,IF(A53>=15000,Premissas!$B$29,IF(A53>=10000,Premissas!$B$28,IF(A53>=5000,Premissas!$B$27,0))))) -> 6415.9474 | C53: =B7*2*(1-Premissas!$B$9)*(1-IF(A53>=20000,Premissas!$B$30,IF(A53>=15000,Premissas!$B$29,IF(A53>=10000,Premissas!$B$28,IF(A53>=5000,Premissas!$B$27,0))))) -> 12446.938 | D53: =B7*3*(1-Premissas!$B$10)*(1-IF(A53>=20000,Premissas!$B$30,IF(A53>=15000,Premissas!$B$29,IF(A53>=10000,Premissas!$B$28,IF(A53>=5000,Premissas!$B$27,0))))) -> 18285.45 | E53: =B7*4*(1-Premissas!$B$11)*(1-IF(A53>=20000,Premissas!$B$30,IF(A53>=15000,Premissas!$B$29,IF(A53>=10000,Premissas!$B$28,IF(A53>=5000,Premissas!$B$27,0))))) -> 23867.324 | F53: =B7*5*(1-Premissas!$B$12)*(1-IF(A53>=20000,Premissas!$B$30,IF(A53>=15000,Premissas!$B$29,IF(A53>=10000,Premissas!$B$28,IF(A53>=5000,Premissas!$B$27,0))))) -> 29192.561 | G53: =B7*6*(1-Premissas!$B$13)*(1-IF(A53>=20000,Premissas!$B$30,IF(A53>=15000,Premissas!$B$29,IF(A53>=10000,Premissas!$B$28,IF(A53>=5000,Premissas!$B$27,0))))) -> 34261.159 | H53: =B7*7*(1-Premissas!$B$14)*(1-IF(A53>=20000,Premissas!$B$30,IF(A53>=15000,Premissas!$B$29,IF(A53>=10000,Premissas!$B$28,IF(A53>=5000,Premissas!$B$27,0))))) -> 39073.119 | I53: =B7*8*(1-Premissas!$B$15)*(1-IF(A53>=20000,Premissas!$B$30,IF(A53>=15000,Premissas!$B$29,IF(A53>=10000,Premissas!$B$28,IF(A53>=5000,Premissas!$B$27,0))))) -> 43628.442 | J53: =B7*9*(1-Premissas!$B$16)*(1-IF(A53>=20000,Premissas!$B$30,IF(A53>=15000,Premissas!$B$29,IF(A53>=10000,Premissas!$B$28,IF(A53>=5000,Premissas!$B$27,0))))) -> 47927.127 | K53: =B7*10*(1-Premissas!$B$17)*(1-IF(A53>=20000,Premissas!$B$30,IF(A53>=15000,Premissas!$B$29,IF(A53>=10000,Premissas!$B$28,IF(A53>=5000,Premissas!$B$27,0))))) -> 51969.174 | L53: =B7*11*(1-Premissas!$B$18)*(1-IF(A53>=20000,Premissas!$B$30,IF(A53>=15000,Premissas!$B$29,IF(A53>=10000,Premissas!$B$28,IF(A53>=5000,Premissas!$B$27,0))))) -> 55754.583 | M53: =B7*12*(1-Premissas!$B$19)*(1-IF(A53>=20000,Premissas!$B$30,IF(A53>=15000,Premissas!$B$29,IF(A53>=10000,Premissas!$B$28,IF(A53>=5000,Premissas!$B$27,0))))) -> 59283.354 | N53: =B7*13*(1-Premissas!$B$20)*(1-IF(A53>=20000,Premissas!$B$30,IF(A53>=15000,Premissas!$B$29,IF(A53>=10000,Premissas!$B$28,IF(A53>=5000,Premissas!$B$27,0))))) -> 62555.487
A54: =Premissas!A37 -> 4000 | B54: =B8*(1-IF(A54>=20000,Premissas!$B$30,IF(A54>=15000,Premissas!$B$29,IF(A54>=10000,Premissas!$B$28,IF(A54>=5000,Premissas!$B$27,0))))) -> 8419 | C54: =B8*2*(1-Premissas!$B$9)*(1-IF(A54>=20000,Premissas!$B$30,IF(A54>=15000,Premissas!$B$29,IF(A54>=10000,Premissas!$B$28,IF(A54>=5000,Premissas!$B$27,0))))) -> 16332.86 | D54: =B8*3*(1-Premissas!$B$10)*(1-IF(A54>=20000,Premissas!$B$30,IF(A54>=15000,Premissas!$B$29,IF(A54>=10000,Premissas!$B$28,IF(A54>=5000,Premissas!$B$27,0))))) -> 23994.15 | E54: =B8*4*(1-Premissas!$B$11)*(1-IF(A54>=20000,Premissas!$B$30,IF(A54>=15000,Premissas!$B$29,IF(A54>=10000,Premissas!$B$28,IF(A54>=5000,Premissas!$B$27,0))))) -> 31318.68 | F54: =B8*5*(1-Premissas!$B$12)*(1-IF(A54>=20000,Premissas!$B$30,IF(A54>=15000,Premissas!$B$29,IF(A54>=10000,Premissas!$B$28,IF(A54>=5000,Premissas!$B$27,0))))) -> 38306.45 | G54: =B8*6*(1-Premissas!$B$13)*(1-IF(A54>=20000,Premissas!$B$30,IF(A54>=15000,Premissas!$B$29,IF(A54>=10000,Premissas!$B$28,IF(A54>=5000,Premissas!$B$27,0))))) -> 44957.46 | H54: =B8*7*(1-Premissas!$B$14)*(1-IF(A54>=20000,Premissas!$B$30,IF(A54>=15000,Premissas!$B$29,IF(A54>=10000,Premissas!$B$28,IF(A54>=5000,Premissas!$B$27,0))))) -> 51271.71 | I54: =B8*8*(1-Premissas!$B$15)*(1-IF(A54>=20000,Premissas!$B$30,IF(A54>=15000,Premissas!$B$29,IF(A54>=10000,Premissas!$B$28,IF(A54>=5000,Premissas!$B$27,0))))) -> 57249.2 | J54: =B8*9*(1-Premissas!$B$16)*(1-IF(A54>=20000,Premissas!$B$30,IF(A54>=15000,Premissas!$B$29,IF(A54>=10000,Premissas!$B$28,IF(A54>=5000,Premissas!$B$27,0))))) -> 62889.93 | K54: =B8*10*(1-Premissas!$B$17)*(1-IF(A54>=20000,Premissas!$B$30,IF(A54>=15000,Premissas!$B$29,IF(A54>=10000,Premissas!$B$28,IF(A54>=5000,Premissas!$B$27,0))))) -> 68193.9 | L54: =B8*11*(1-Premissas!$B$18)*(1-IF(A54>=20000,Premissas!$B$30,IF(A54>=15000,Premissas!$B$29,IF(A54>=10000,Premissas!$B$28,IF(A54>=5000,Premissas!$B$27,0))))) -> 73161.11 | M54: =B8*12*(1-Premissas!$B$19)*(1-IF(A54>=20000,Premissas!$B$30,IF(A54>=15000,Premissas!$B$29,IF(A54>=10000,Premissas!$B$28,IF(A54>=5000,Premissas!$B$27,0))))) -> 77791.56 | N54: =B8*13*(1-Premissas!$B$20)*(1-IF(A54>=20000,Premissas!$B$30,IF(A54>=15000,Premissas!$B$29,IF(A54>=10000,Premissas!$B$28,IF(A54>=5000,Premissas!$B$27,0))))) -> 82085.25
A55: =Premissas!A38 -> 5000 | B55: =B9*(1-IF(A55>=20000,Premissas!$B$30,IF(A55>=15000,Premissas!$B$29,IF(A55>=10000,Premissas!$B$28,IF(A55>=5000,Premissas!$B$27,0))))) -> 9774.6842 | C55: =B9*2*(1-Premissas!$B$9)*(1-IF(A55>=20000,Premissas!$B$30,IF(A55>=15000,Premissas!$B$29,IF(A55>=10000,Premissas!$B$28,IF(A55>=5000,Premissas!$B$27,0))))) -> 18962.887 | D55: =B9*3*(1-Premissas!$B$10)*(1-IF(A55>=20000,Premissas!$B$30,IF(A55>=15000,Premissas!$B$29,IF(A55>=10000,Premissas!$B$28,IF(A55>=5000,Premissas!$B$27,0))))) -> 27857.85 | E55: =B9*4*(1-Premissas!$B$11)*(1-IF(A55>=20000,Premissas!$B$30,IF(A55>=15000,Premissas!$B$29,IF(A55>=10000,Premissas!$B$28,IF(A55>=5000,Premissas!$B$27,0))))) -> 36361.825 | F55: =B9*5*(1-Premissas!$B$12)*(1-IF(A55>=20000,Premissas!$B$30,IF(A55>=15000,Premissas!$B$29,IF(A55>=10000,Premissas!$B$28,IF(A55>=5000,Premissas!$B$27,0))))) -> 44474.813 | G55: =B9*6*(1-Premissas!$B$13)*(1-IF(A55>=20000,Premissas!$B$30,IF(A55>=15000,Premissas!$B$29,IF(A55>=10000,Premissas!$B$28,IF(A55>=5000,Premissas!$B$27,0))))) -> 52196.814 | H55: =B9*7*(1-Premissas!$B$14)*(1-IF(A55>=20000,Premissas!$B$30,IF(A55>=15000,Premissas!$B$29,IF(A55>=10000,Premissas!$B$28,IF(A55>=5000,Premissas!$B$27,0))))) -> 59527.827 | I55: =B9*8*(1-Premissas!$B$15)*(1-IF(A55>=20000,Premissas!$B$30,IF(A55>=15000,Premissas!$B$29,IF(A55>=10000,Premissas!$B$28,IF(A55>=5000,Premissas!$B$27,0))))) -> 66467.853 | J55: =B9*9*(1-Premissas!$B$16)*(1-IF(A55>=20000,Premissas!$B$30,IF(A55>=15000,Premissas!$B$29,IF(A55>=10000,Premissas!$B$28,IF(A55>=5000,Premissas!$B$27,0))))) -> 73016.891 | K55: =B9*10*(1-Premissas!$B$17)*(1-IF(A55>=20000,Premissas!$B$30,IF(A55>=15000,Premissas!$B$29,IF(A55>=10000,Premissas!$B$28,IF(A55>=5000,Premissas!$B$27,0))))) -> 79174.942 | L55: =B9*11*(1-Premissas!$B$18)*(1-IF(A55>=20000,Premissas!$B$30,IF(A55>=15000,Premissas!$B$29,IF(A55>=10000,Premissas!$B$28,IF(A55>=5000,Premissas!$B$27,0))))) -> 84942.006 | M55: =B9*12*(1-Premissas!$B$19)*(1-IF(A55>=20000,Premissas!$B$30,IF(A55>=15000,Premissas!$B$29,IF(A55>=10000,Premissas!$B$28,IF(A55>=5000,Premissas!$B$27,0))))) -> 90318.082 | N55: =B9*13*(1-Premissas!$B$20)*(1-IF(A55>=20000,Premissas!$B$30,IF(A55>=15000,Premissas!$B$29,IF(A55>=10000,Premissas!$B$28,IF(A55>=5000,Premissas!$B$27,0))))) -> 95303.171
A56: =Premissas!A39 -> 6000 | B56: =B10*(1-IF(A56>=20000,Premissas!$B$30,IF(A56>=15000,Premissas!$B$29,IF(A56>=10000,Premissas!$B$28,IF(A56>=5000,Premissas!$B$27,0))))) -> 11778.211 | C56: =B10*2*(1-Premissas!$B$9)*(1-IF(A56>=20000,Premissas!$B$30,IF(A56>=15000,Premissas!$B$29,IF(A56>=10000,Premissas!$B$28,IF(A56>=5000,Premissas!$B$27,0))))) -> 22849.728 | D56: =B10*3*(1-Premissas!$B$10)*(1-IF(A56>=20000,Premissas!$B$30,IF(A56>=15000,Premissas!$B$29,IF(A56>=10000,Premissas!$B$28,IF(A56>=5000,Premissas!$B$27,0))))) -> 33567.9 | E56: =B10*4*(1-Premissas!$B$11)*(1-IF(A56>=20000,Premissas!$B$30,IF(A56>=15000,Premissas!$B$29,IF(A56>=10000,Premissas!$B$28,IF(A56>=5000,Premissas!$B$27,0))))) -> 43814.943 | F56: =B10*5*(1-Premissas!$B$12)*(1-IF(A56>=20000,Premissas!$B$30,IF(A56>=15000,Premissas!$B$29,IF(A56>=10000,Premissas!$B$28,IF(A56>=5000,Premissas!$B$27,0))))) -> 53590.858 | G56: =B10*6*(1-Premissas!$B$13)*(1-IF(A56>=20000,Premissas!$B$30,IF(A56>=15000,Premissas!$B$29,IF(A56>=10000,Premissas!$B$28,IF(A56>=5000,Premissas!$B$27,0))))) -> 62895.644 | H56: =B10*7*(1-Premissas!$B$14)*(1-IF(A56>=20000,Premissas!$B$30,IF(A56>=15000,Premissas!$B$29,IF(A56>=10000,Premissas!$B$28,IF(A56>=5000,Premissas!$B$27,0))))) -> 71729.302 | I56: =B10*8*(1-Premissas!$B$15)*(1-IF(A56>=20000,Premissas!$B$30,IF(A56>=15000,Premissas!$B$29,IF(A56>=10000,Premissas!$B$28,IF(A56>=5000,Premissas!$B$27,0))))) -> 80091.832 | J56: =B10*9*(1-Premissas!$B$16)*(1-IF(A56>=20000,Premissas!$B$30,IF(A56>=15000,Premissas!$B$29,IF(A56>=10000,Premissas!$B$28,IF(A56>=5000,Premissas!$B$27,0))))) -> 87983.233 | K56: =B10*10*(1-Premissas!$B$17)*(1-IF(A56>=20000,Premissas!$B$30,IF(A56>=15000,Premissas!$B$29,IF(A56>=10000,Premissas!$B$28,IF(A56>=5000,Premissas!$B$27,0))))) -> 95403.505 | L56: =B10*11*(1-Premissas!$B$18)*(1-IF(A56>=20000,Premissas!$B$30,IF(A56>=15000,Premissas!$B$29,IF(A56>=10000,Premissas!$B$28,IF(A56>=5000,Premissas!$B$27,0))))) -> 102352.65 | M56: =B10*12*(1-Premissas!$B$19)*(1-IF(A56>=20000,Premissas!$B$30,IF(A56>=15000,Premissas!$B$29,IF(A56>=10000,Premissas!$B$28,IF(A56>=5000,Premissas!$B$27,0))))) -> 108830.67 | N56: =B10*13*(1-Premissas!$B$20)*(1-IF(A56>=20000,Premissas!$B$30,IF(A56>=15000,Premissas!$B$29,IF(A56>=10000,Premissas!$B$28,IF(A56>=5000,Premissas!$B$27,0))))) -> 114837.55
A57: =Premissas!A40 -> 7000 | B57: =B11*(1-IF(A57>=20000,Premissas!$B$30,IF(A57>=15000,Premissas!$B$29,IF(A57>=10000,Premissas!$B$28,IF(A57>=5000,Premissas!$B$27,0))))) -> 13779.158 | C57: =B11*2*(1-Premissas!$B$9)*(1-IF(A57>=20000,Premissas!$B$30,IF(A57>=15000,Premissas!$B$29,IF(A57>=10000,Premissas!$B$28,IF(A57>=5000,Premissas!$B$27,0))))) -> 26731.566 | D57: =B11*3*(1-Premissas!$B$10)*(1-IF(A57>=20000,Premissas!$B$30,IF(A57>=15000,Premissas!$B$29,IF(A57>=10000,Premissas!$B$28,IF(A57>=5000,Premissas!$B$27,0))))) -> 39270.6 | E57: =B11*4*(1-Premissas!$B$11)*(1-IF(A57>=20000,Premissas!$B$30,IF(A57>=15000,Premissas!$B$29,IF(A57>=10000,Premissas!$B$28,IF(A57>=5000,Premissas!$B$27,0))))) -> 51258.467 | F57: =B11*5*(1-Premissas!$B$12)*(1-IF(A57>=20000,Premissas!$B$30,IF(A57>=15000,Premissas!$B$29,IF(A57>=10000,Premissas!$B$28,IF(A57>=5000,Premissas!$B$27,0))))) -> 62695.168 | G57: =B11*6*(1-Premissas!$B$13)*(1-IF(A57>=20000,Premissas!$B$30,IF(A57>=15000,Premissas!$B$29,IF(A57>=10000,Premissas!$B$28,IF(A57>=5000,Premissas!$B$27,0))))) -> 73580.703 | H57: =B11*7*(1-Premissas!$B$14)*(1-IF(A57>=20000,Premissas!$B$30,IF(A57>=15000,Premissas!$B$29,IF(A57>=10000,Premissas!$B$28,IF(A57>=5000,Premissas!$B$27,0))))) -> 83915.072 | I57: =B11*8*(1-Premissas!$B$15)*(1-IF(A57>=20000,Premissas!$B$30,IF(A57>=15000,Premissas!$B$29,IF(A57>=10000,Premissas!$B$28,IF(A57>=5000,Premissas!$B$27,0))))) -> 93698.274 | J57: =B11*9*(1-Premissas!$B$16)*(1-IF(A57>=20000,Premissas!$B$30,IF(A57>=15000,Premissas!$B$29,IF(A57>=10000,Premissas!$B$28,IF(A57>=5000,Premissas!$B$27,0))))) -> 102930.31 | K57: =B11*10*(1-Premissas!$B$17)*(1-IF(A57>=20000,Premissas!$B$30,IF(A57>=15000,Premissas!$B$29,IF(A57>=10000,Premissas!$B$28,IF(A57>=5000,Premissas!$B$27,0))))) -> 111611.18 | L57: =B11*11*(1-Premissas!$B$18)*(1-IF(A57>=20000,Premissas!$B$30,IF(A57>=15000,Premissas!$B$29,IF(A57>=10000,Premissas!$B$28,IF(A57>=5000,Premissas!$B$27,0))))) -> 119740.88 | M57: =B11*12*(1-Premissas!$B$19)*(1-IF(A57>=20000,Premissas!$B$30,IF(A57>=15000,Premissas!$B$29,IF(A57>=10000,Premissas!$B$28,IF(A57>=5000,Premissas!$B$27,0))))) -> 127319.42 | N57: =B11*13*(1-Premissas!$B$20)*(1-IF(A57>=20000,Premissas!$B$30,IF(A57>=15000,Premissas!$B$29,IF(A57>=10000,Premissas!$B$28,IF(A57>=5000,Premissas!$B$27,0))))) -> 134346.79
A58: =Premissas!A41 -> 8000 | B58: =B12*(1-IF(A58>=20000,Premissas!$B$30,IF(A58>=15000,Premissas!$B$29,IF(A58>=10000,Premissas!$B$28,IF(A58>=5000,Premissas!$B$27,0))))) -> 15661.158 | C58: =B12*2*(1-Premissas!$B$9)*(1-IF(A58>=20000,Premissas!$B$30,IF(A58>=15000,Premissas!$B$29,IF(A58>=10000,Premissas!$B$28,IF(A58>=5000,Premissas!$B$27,0))))) -> 30382.646 | D58: =B12*3*(1-Premissas!$B$10)*(1-IF(A58>=20000,Premissas!$B$30,IF(A58>=15000,Premissas!$B$29,IF(A58>=10000,Premissas!$B$28,IF(A58>=5000,Premissas!$B$27,0))))) -> 44634.3 | E58: =B12*4*(1-Premissas!$B$11)*(1-IF(A58>=20000,Premissas!$B$30,IF(A58>=15000,Premissas!$B$29,IF(A58>=10000,Premissas!$B$28,IF(A58>=5000,Premissas!$B$27,0))))) -> 58259.507 | F58: =B12*5*(1-Premissas!$B$12)*(1-IF(A58>=20000,Premissas!$B$30,IF(A58>=15000,Premissas!$B$29,IF(A58>=10000,Premissas!$B$28,IF(A58>=5000,Premissas!$B$27,0))))) -> 71258.268 | G58: =B12*6*(1-Premissas!$B$13)*(1-IF(A58>=20000,Premissas!$B$30,IF(A58>=15000,Premissas!$B$29,IF(A58>=10000,Premissas!$B$28,IF(A58>=5000,Premissas!$B$27,0))))) -> 83630.583 | H58: =B12*7*(1-Premissas!$B$14)*(1-IF(A58>=20000,Premissas!$B$30,IF(A58>=15000,Premissas!$B$29,IF(A58>=10000,Premissas!$B$28,IF(A58>=5000,Premissas!$B$27,0))))) -> 95376.452 | I58: =B12*8*(1-Premissas!$B$15)*(1-IF(A58>=20000,Premissas!$B$30,IF(A58>=15000,Premissas!$B$29,IF(A58>=10000,Premissas!$B$28,IF(A58>=5000,Premissas!$B$27,0))))) -> 106495.87 | J58: =B12*9*(1-Premissas!$B$16)*(1-IF(A58>=20000,Premissas!$B$30,IF(A58>=15000,Premissas!$B$29,IF(A58>=10000,Premissas!$B$28,IF(A58>=5000,Premissas!$B$27,0))))) -> 116988.85 | K58: =B12*10*(1-Premissas!$B$17)*(1-IF(A58>=20000,Premissas!$B$30,IF(A58>=15000,Premissas!$B$29,IF(A58>=10000,Premissas!$B$28,IF(A58>=5000,Premissas!$B$27,0))))) -> 126855.38 | L58: =B12*11*(1-Premissas!$B$18)*(1-IF(A58>=20000,Premissas!$B$30,IF(A58>=15000,Premissas!$B$29,IF(A58>=10000,Premissas!$B$28,IF(A58>=5000,Premissas!$B$27,0))))) -> 136095.46 | M58: =B12*12*(1-Premissas!$B$19)*(1-IF(A58>=20000,Premissas!$B$30,IF(A58>=15000,Premissas!$B$29,IF(A58>=10000,Premissas!$B$28,IF(A58>=5000,Premissas!$B$27,0))))) -> 144709.1 | N58: =B12*13*(1-Premissas!$B$20)*(1-IF(A58>=20000,Premissas!$B$30,IF(A58>=15000,Premissas!$B$29,IF(A58>=10000,Premissas!$B$28,IF(A58>=5000,Premissas!$B$27,0))))) -> 152696.29
A59: =Premissas!A42 -> 9000 | B59: =B13*(1-IF(A59>=20000,Premissas!$B$30,IF(A59>=15000,Premissas!$B$29,IF(A59>=10000,Premissas!$B$28,IF(A59>=5000,Premissas!$B$27,0))))) -> 17664.684 | C59: =B13*2*(1-Premissas!$B$9)*(1-IF(A59>=20000,Premissas!$B$30,IF(A59>=15000,Premissas!$B$29,IF(A59>=10000,Premissas!$B$28,IF(A59>=5000,Premissas!$B$27,0))))) -> 34269.487 | D59: =B13*3*(1-Premissas!$B$10)*(1-IF(A59>=20000,Premissas!$B$30,IF(A59>=15000,Premissas!$B$29,IF(A59>=10000,Premissas!$B$28,IF(A59>=5000,Premissas!$B$27,0))))) -> 50344.35 | E59: =B13*4*(1-Premissas!$B$11)*(1-IF(A59>=20000,Premissas!$B$30,IF(A59>=15000,Premissas!$B$29,IF(A59>=10000,Premissas!$B$28,IF(A59>=5000,Premissas!$B$27,0))))) -> 65712.625 | F59: =B13*5*(1-Premissas!$B$12)*(1-IF(A59>=20000,Premissas!$B$30,IF(A59>=15000,Premissas!$B$29,IF(A59>=10000,Premissas!$B$28,IF(A59>=5000,Premissas!$B$27,0))))) -> 80374.313 | G59: =B13*6*(1-Premissas!$B$13)*(1-IF(A59>=20000,Premissas!$B$30,IF(A59>=15000,Premissas!$B$29,IF(A59>=10000,Premissas!$B$28,IF(A59>=5000,Premissas!$B$27,0))))) -> 94329.414 | H59: =B13*7*(1-Premissas!$B$14)*(1-IF(A59>=20000,Premissas!$B$30,IF(A59>=15000,Premissas!$B$29,IF(A59>=10000,Premissas!$B$28,IF(A59>=5000,Premissas!$B$27,0))))) -> 107577.93 | I59: =B13*8*(1-Premissas!$B$15)*(1-IF(A59>=20000,Premissas!$B$30,IF(A59>=15000,Premissas!$B$29,IF(A59>=10000,Premissas!$B$28,IF(A59>=5000,Premissas!$B$27,0))))) -> 120119.85 | J59: =B13*9*(1-Premissas!$B$16)*(1-IF(A59>=20000,Premissas!$B$30,IF(A59>=15000,Premissas!$B$29,IF(A59>=10000,Premissas!$B$28,IF(A59>=5000,Premissas!$B$27,0))))) -> 131955.19 | K59: =B13*10*(1-Premissas!$B$17)*(1-IF(A59>=20000,Premissas!$B$30,IF(A59>=15000,Premissas!$B$29,IF(A59>=10000,Premissas!$B$28,IF(A59>=5000,Premissas!$B$27,0))))) -> 143083.94 | L59: =B13*11*(1-Premissas!$B$18)*(1-IF(A59>=20000,Premissas!$B$30,IF(A59>=15000,Premissas!$B$29,IF(A59>=10000,Premissas!$B$28,IF(A59>=5000,Premissas!$B$27,0))))) -> 153506.11 | M59: =B13*12*(1-Premissas!$B$19)*(1-IF(A59>=20000,Premissas!$B$30,IF(A59>=15000,Premissas!$B$29,IF(A59>=10000,Premissas!$B$28,IF(A59>=5000,Premissas!$B$27,0))))) -> 163221.68 | N59: =B13*13*(1-Premissas!$B$20)*(1-IF(A59>=20000,Premissas!$B$30,IF(A59>=15000,Premissas!$B$29,IF(A59>=10000,Premissas!$B$28,IF(A59>=5000,Premissas!$B$27,0))))) -> 172230.67
A60: =Premissas!A43 -> 10000 | B60: =B14*(1-IF(A60>=20000,Premissas!$B$30,IF(A60>=15000,Premissas!$B$29,IF(A60>=10000,Premissas!$B$28,IF(A60>=5000,Premissas!$B$27,0))))) -> 18097.211 | C60: =B14*2*(1-Premissas!$B$9)*(1-IF(A60>=20000,Premissas!$B$30,IF(A60>=15000,Premissas!$B$29,IF(A60>=10000,Premissas!$B$28,IF(A60>=5000,Premissas!$B$27,0))))) -> 35108.588 | D60: =B14*3*(1-Premissas!$B$10)*(1-IF(A60>=20000,Premissas!$B$30,IF(A60>=15000,Premissas!$B$29,IF(A60>=10000,Premissas!$B$28,IF(A60>=5000,Premissas!$B$27,0))))) -> 51577.05 | E60: =B14*4*(1-Premissas!$B$11)*(1-IF(A60>=20000,Premissas!$B$30,IF(A60>=15000,Premissas!$B$29,IF(A60>=10000,Premissas!$B$28,IF(A60>=5000,Premissas!$B$27,0))))) -> 67321.623 | F60: =B14*5*(1-Premissas!$B$12)*(1-IF(A60>=20000,Premissas!$B$30,IF(A60>=15000,Premissas!$B$29,IF(A60>=10000,Premissas!$B$28,IF(A60>=5000,Premissas!$B$27,0))))) -> 82342.308 | G60: =B14*6*(1-Premissas!$B$13)*(1-IF(A60>=20000,Premissas!$B$30,IF(A60>=15000,Premissas!$B$29,IF(A60>=10000,Premissas!$B$28,IF(A60>=5000,Premissas!$B$27,0))))) -> 96639.104 | H60: =B14*7*(1-Premissas!$B$14)*(1-IF(A60>=20000,Premissas!$B$30,IF(A60>=15000,Premissas!$B$29,IF(A60>=10000,Premissas!$B$28,IF(A60>=5000,Premissas!$B$27,0))))) -> 110212.01 | I60: =B14*8*(1-Premissas!$B$15)*(1-IF(A60>=20000,Premissas!$B$30,IF(A60>=15000,Premissas!$B$29,IF(A60>=10000,Premissas!$B$28,IF(A60>=5000,Premissas!$B$27,0))))) -> 123061.03 | J60: =B14*9*(1-Premissas!$B$16)*(1-IF(A60>=20000,Premissas!$B$30,IF(A60>=15000,Premissas!$B$29,IF(A60>=10000,Premissas!$B$28,IF(A60>=5000,Premissas!$B$27,0))))) -> 135186.16 | K60: =B14*10*(1-Premissas!$B$17)*(1-IF(A60>=20000,Premissas!$B$30,IF(A60>=15000,Premissas!$B$29,IF(A60>=10000,Premissas!$B$28,IF(A60>=5000,Premissas!$B$27,0))))) -> 146587.41 | L60: =B14*11*(1-Premissas!$B$18)*(1-IF(A60>=20000,Premissas!$B$30,IF(A60>=15000,Premissas!$B$29,IF(A60>=10000,Premissas!$B$28,IF(A60>=5000,Premissas!$B$27,0))))) -> 157264.76 | M60: =B14*12*(1-Premissas!$B$19)*(1-IF(A60>=20000,Premissas!$B$30,IF(A60>=15000,Premissas!$B$29,IF(A60>=10000,Premissas!$B$28,IF(A60>=5000,Premissas!$B$27,0))))) -> 167218.23 | N60: =B14*13*(1-Premissas!$B$20)*(1-IF(A60>=20000,Premissas!$B$30,IF(A60>=15000,Premissas!$B$29,IF(A60>=10000,Premissas!$B$28,IF(A60>=5000,Premissas!$B$27,0))))) -> 176447.8
A61: =Premissas!A44 -> 11000 | B61: =B15*(1-IF(A61>=20000,Premissas!$B$30,IF(A61>=15000,Premissas!$B$29,IF(A61>=10000,Premissas!$B$28,IF(A61>=5000,Premissas!$B$27,0))))) -> 20248 | C61: =B15*2*(1-Premissas!$B$9)*(1-IF(A61>=20000,Premissas!$B$30,IF(A61>=15000,Premissas!$B$29,IF(A61>=10000,Premissas!$B$28,IF(A61>=5000,Premissas!$B$27,0))))) -> 39281.12 | D61: =B15*3*(1-Premissas!$B$10)*(1-IF(A61>=20000,Premissas!$B$30,IF(A61>=15000,Premissas!$B$29,IF(A61>=10000,Premissas!$B$28,IF(A61>=5000,Premissas!$B$27,0))))) -> 57706.8 | E61: =B15*4*(1-Premissas!$B$11)*(1-IF(A61>=20000,Premissas!$B$30,IF(A61>=15000,Premissas!$B$29,IF(A61>=10000,Premissas!$B$28,IF(A61>=5000,Premissas!$B$27,0))))) -> 75322.56 | F61: =B15*5*(1-Premissas!$B$12)*(1-IF(A61>=20000,Premissas!$B$30,IF(A61>=15000,Premissas!$B$29,IF(A61>=10000,Premissas!$B$28,IF(A61>=5000,Premissas!$B$27,0))))) -> 92128.4 | G61: =B15*6*(1-Premissas!$B$13)*(1-IF(A61>=20000,Premissas!$B$30,IF(A61>=15000,Premissas!$B$29,IF(A61>=10000,Premissas!$B$28,IF(A61>=5000,Premissas!$B$27,0))))) -> 108124.32 | H61: =B15*7*(1-Premissas!$B$14)*(1-IF(A61>=20000,Premissas!$B$30,IF(A61>=15000,Premissas!$B$29,IF(A61>=10000,Premissas!$B$28,IF(A61>=5000,Premissas!$B$27,0))))) -> 123310.32 | I61: =B15*8*(1-Premissas!$B$15)*(1-IF(A61>=20000,Premissas!$B$30,IF(A61>=15000,Premissas!$B$29,IF(A61>=10000,Premissas!$B$28,IF(A61>=5000,Premissas!$B$27,0))))) -> 137686.4 | J61: =B15*9*(1-Premissas!$B$16)*(1-IF(A61>=20000,Premissas!$B$30,IF(A61>=15000,Premissas!$B$29,IF(A61>=10000,Premissas!$B$28,IF(A61>=5000,Premissas!$B$27,0))))) -> 151252.56 | K61: =B15*10*(1-Premissas!$B$17)*(1-IF(A61>=20000,Premissas!$B$30,IF(A61>=15000,Premissas!$B$29,IF(A61>=10000,Premissas!$B$28,IF(A61>=5000,Premissas!$B$27,0))))) -> 164008.8 | L61: =B15*11*(1-Premissas!$B$18)*(1-IF(A61>=20000,Premissas!$B$30,IF(A61>=15000,Premissas!$B$29,IF(A61>=10000,Premissas!$B$28,IF(A61>=5000,Premissas!$B$27,0))))) -> 175955.12 | M61: =B15*12*(1-Premissas!$B$19)*(1-IF(A61>=20000,Premissas!$B$30,IF(A61>=15000,Premissas!$B$29,IF(A61>=10000,Premissas!$B$28,IF(A61>=5000,Premissas!$B$27,0))))) -> 187091.52 | N61: =B15*13*(1-Premissas!$B$20)*(1-IF(A61>=20000,Premissas!$B$30,IF(A61>=15000,Premissas!$B$29,IF(A61>=10000,Premissas!$B$28,IF(A61>=5000,Premissas!$B$27,0))))) -> 197418
A62: =Premissas!A45 -> 12000 | B62: =B16*(1-IF(A62>=20000,Premissas!$B$30,IF(A62>=15000,Premissas!$B$29,IF(A62>=10000,Premissas!$B$28,IF(A62>=5000,Premissas!$B$27,0))))) -> 22092.105 | C62: =B16*2*(1-Premissas!$B$9)*(1-IF(A62>=20000,Premissas!$B$30,IF(A62>=15000,Premissas!$B$29,IF(A62>=10000,Premissas!$B$28,IF(A62>=5000,Premissas!$B$27,0))))) -> 42858.684 | D62: =B16*3*(1-Premissas!$B$10)*(1-IF(A62>=20000,Premissas!$B$30,IF(A62>=15000,Premissas!$B$29,IF(A62>=10000,Premissas!$B$28,IF(A62>=5000,Premissas!$B$27,0))))) -> 62962.5 | E62: =B16*4*(1-Premissas!$B$11)*(1-IF(A62>=20000,Premissas!$B$30,IF(A62>=15000,Premissas!$B$29,IF(A62>=10000,Premissas!$B$28,IF(A62>=5000,Premissas!$B$27,0))))) -> 82182.632 | F62: =B16*5*(1-Premissas!$B$12)*(1-IF(A62>=20000,Premissas!$B$30,IF(A62>=15000,Premissas!$B$29,IF(A62>=10000,Premissas!$B$28,IF(A62>=5000,Premissas!$B$27,0))))) -> 100519.08 | G62: =B16*6*(1-Premissas!$B$13)*(1-IF(A62>=20000,Premissas!$B$30,IF(A62>=15000,Premissas!$B$29,IF(A62>=10000,Premissas!$B$28,IF(A62>=5000,Premissas!$B$27,0))))) -> 117971.84 | H62: =B16*7*(1-Premissas!$B$14)*(1-IF(A62>=20000,Premissas!$B$30,IF(A62>=15000,Premissas!$B$29,IF(A62>=10000,Premissas!$B$28,IF(A62>=5000,Premissas!$B$27,0))))) -> 134540.92 | I62: =B16*8*(1-Premissas!$B$15)*(1-IF(A62>=20000,Premissas!$B$30,IF(A62>=15000,Premissas!$B$29,IF(A62>=10000,Premissas!$B$28,IF(A62>=5000,Premissas!$B$27,0))))) -> 150226.32 | J62: =B16*9*(1-Premissas!$B$16)*(1-IF(A62>=20000,Premissas!$B$30,IF(A62>=15000,Premissas!$B$29,IF(A62>=10000,Premissas!$B$28,IF(A62>=5000,Premissas!$B$27,0))))) -> 165028.03 | K62: =B16*10*(1-Premissas!$B$17)*(1-IF(A62>=20000,Premissas!$B$30,IF(A62>=15000,Premissas!$B$29,IF(A62>=10000,Premissas!$B$28,IF(A62>=5000,Premissas!$B$27,0))))) -> 178946.05 | L62: =B16*11*(1-Premissas!$B$18)*(1-IF(A62>=20000,Premissas!$B$30,IF(A62>=15000,Premissas!$B$29,IF(A62>=10000,Premissas!$B$28,IF(A62>=5000,Premissas!$B$27,0))))) -> 191980.39 | M62: =B16*12*(1-Premissas!$B$19)*(1-IF(A62>=20000,Premissas!$B$30,IF(A62>=15000,Premissas!$B$29,IF(A62>=10000,Premissas!$B$28,IF(A62>=5000,Premissas!$B$27,0))))) -> 204131.05 | N62: =B16*13*(1-Premissas!$B$20)*(1-IF(A62>=20000,Premissas!$B$30,IF(A62>=15000,Premissas!$B$29,IF(A62>=10000,Premissas!$B$28,IF(A62>=5000,Premissas!$B$27,0))))) -> 215398.03
... A70: =Premissas!A53 -> 20000 | B70: =B24*(1-IF(A70>=20000,Premissas!$B$30,IF(A70>=15000,Premissas!$B$29,IF(A70>=10000,Premissas!$B$28,IF(A70>=5000,Premissas!$B$27,0))))) -> 35866.263 | C70: =B24*2*(1-Premissas!$B$9)*(1-IF(A70>=20000,Premissas!$B$30,IF(A70>=15000,Premissas!$B$29,IF(A70>=10000,Premissas!$B$28,IF(A70>=5000,Premissas!$B$27,0))))) -> 69580.551 | D70: =B24*3*(1-Premissas!$B$10)*(1-IF(A70>=20000,Premissas!$B$30,IF(A70>=15000,Premissas!$B$29,IF(A70>=10000,Premissas!$B$28,IF(A70>=5000,Premissas!$B$27,0))))) -> 102218.85 | E70: =B24*4*(1-Premissas!$B$11)*(1-IF(A70>=20000,Premissas!$B$30,IF(A70>=15000,Premissas!$B$29,IF(A70>=10000,Premissas!$B$28,IF(A70>=5000,Premissas!$B$27,0))))) -> 133422.5 | F70: =B24*5*(1-Premissas!$B$12)*(1-IF(A70>=20000,Premissas!$B$30,IF(A70>=15000,Premissas!$B$29,IF(A70>=10000,Premissas!$B$28,IF(A70>=5000,Premissas!$B$27,0))))) -> 163191.5 | G70: =B24*6*(1-Premissas!$B$13)*(1-IF(A70>=20000,Premissas!$B$30,IF(A70>=15000,Premissas!$B$29,IF(A70>=10000,Premissas!$B$28,IF(A70>=5000,Premissas!$B$27,0))))) -> 191525.85 | H70: =B24*7*(1-Premissas!$B$14)*(1-IF(A70>=20000,Premissas!$B$30,IF(A70>=15000,Premissas!$B$29,IF(A70>=10000,Premissas!$B$28,IF(A70>=5000,Premissas!$B$27,0))))) -> 218425.54 | I70: =B24*8*(1-Premissas!$B$15)*(1-IF(A70>=20000,Premissas!$B$30,IF(A70>=15000,Premissas!$B$29,IF(A70>=10000,Premissas!$B$28,IF(A70>=5000,Premissas!$B$27,0))))) -> 243890.59 | J70: =B24*9*(1-Premissas!$B$16)*(1-IF(A70>=20000,Premissas!$B$30,IF(A70>=15000,Premissas!$B$29,IF(A70>=10000,Premissas!$B$28,IF(A70>=5000,Premissas!$B$27,0))))) -> 267920.99 | K70: =B24*10*(1-Premissas!$B$17)*(1-IF(A70>=20000,Premissas!$B$30,IF(A70>=15000,Premissas!$B$29,IF(A70>=10000,Premissas!$B$28,IF(A70>=5000,Premissas!$B$27,0))))) -> 290516.73 | L70: =B24*11*(1-Premissas!$B$18)*(1-IF(A70>=20000,Premissas!$B$30,IF(A70>=15000,Premissas!$B$29,IF(A70>=10000,Premissas!$B$28,IF(A70>=5000,Premissas!$B$27,0))))) -> 311677.83 | M70: =B24*12*(1-Premissas!$B$19)*(1-IF(A70>=20000,Premissas!$B$30,IF(A70>=15000,Premissas!$B$29,IF(A70>=10000,Premissas!$B$28,IF(A70>=5000,Premissas!$B$27,0))))) -> 331404.27 | N70: =B24*13*(1-Premissas!$B$20)*(1-IF(A70>=20000,Premissas!$B$30,IF(A70>=15000,Premissas!$B$29,IF(A70>=10000,Premissas!$B$28,IF(A70>=5000,Premissas!$B$27,0))))) -> 349696.07
A72: MATRIZ DE DESCONTOS COMBINADOS: Quantidade + Prazo (% sobre preço base 1.000 un / 4 sem)
A73: Volume | B73: 4 sem | C73: 8 sem | D73: 12 sem | E73: 16 sem | F73: 20 sem | G73: 24 sem | H73: 28 sem | I73: 32 sem | J73: 36 sem | K73: 40 sem | L73: 44 sem | M73: 48 sem | N73: 52 sem
A74: =A28 -> 1000 | B74: =1-(C28/C$28) -> 0 | C74: =1-(D28/C$28) -> 0.03 | D74: =1-(E28/C$28) -> 0.05 | E74: =1-(F28/C$28) -> 0.07 | F74: =1-(G28/C$28) -> 0.09 | G74: =1-(H28/C$28) -> 0.11 | H74: =1-(I28/C$28) -> 0.13 | I74: =1-(J28/C$28) -> 0.15 | J74: =1-(K28/C$28) -> 0.17 | K74: =1-(L28/C$28) -> 0.19 | L74: =1-(M28/C$28) -> 0.21 | M74: =1-(N28/C$28) -> 0.23 | N74: =1-(O28/C$28) -> 0.25
A75: =A29 -> 2000 | B75: =1-(C29/C$28) -> 0.16247652 | C75: =1-(D29/C$28) -> 0.18760222 | D75: =1-(E29/C$28) -> 0.20435269 | E75: =1-(F29/C$28) -> 0.22110316 | F75: =1-(G29/C$28) -> 0.23785363 | G75: =1-(H29/C$28) -> 0.2546041 | H75: =1-(I29/C$28) -> 0.27135457 | I75: =1-(J29/C$28) -> 0.28810504 | J75: =1-(K29/C$28) -> 0.30485551 | K75: =1-(L29/C$28) -> 0.32160598 | L75: =1-(M29/C$28) -> 0.33835645 | M75: =1-(N29/C$28) -> 0.35510692 | N75: =1-(O29/C$28) -> 0.37185739
A76: =A30 -> 3000 | B76: =1-(C30/C$28) -> 0.18793051 | C76: =1-(D30/C$28) -> 0.21229259 | D76: =1-(E30/C$28) -> 0.22853398 | E76: =1-(F30/C$28) -> 0.24477537 | F76: =1-(G30/C$28) -> 0.26101676 | G76: =1-(H30/C$28) -> 0.27725815 | H76: =1-(I30/C$28) -> 0.29349954 | I76: =1-(J30/C$28) -> 0.30974093 | J76: =1-(K30/C$28) -> 0.32598232 | K76: =1-(L30/C$28) -> 0.34222371 | L76: =1-(M30/C$28) -> 0.3584651 | M76: =1-(N30/C$28) -> 0.37470649 | N76: =1-(O30/C$28) -> 0.39094788
A77: =A31 -> 4000 | B77: =1-(C31/C$28) -> 0.20080239 | C77: =1-(D31/C$28) -> 0.22477832 | D77: =1-(E31/C$28) -> 0.24076227 | E77: =1-(F31/C$28) -> 0.25674622 | F77: =1-(G31/C$28) -> 0.27273018 | G77: =1-(H31/C$28) -> 0.28871413 | H77: =1-(I31/C$28) -> 0.30469808 | I77: =1-(J31/C$28) -> 0.32068203 | J77: =1-(K31/C$28) -> 0.33666598 | K77: =1-(L31/C$28) -> 0.35264994 | L77: =1-(M31/C$28) -> 0.36863389 | M77: =1-(N31/C$28) -> 0.38461784 | N77: =1-(O31/C$28) -> 0.40060179
A78: =A32 -> 5000 | B78: =1-(C32/C$28) -> 0.25768816 | C78: =1-(D32/C$28) -> 0.27995751 | D78: =1-(E32/C$28) -> 0.29480375 | E78: =1-(F32/C$28) -> 0.30964999 | F78: =1-(G32/C$28) -> 0.32449622 | G78: =1-(H32/C$28) -> 0.33934246 | H78: =1-(I32/C$28) -> 0.3541887 | I78: =1-(J32/C$28) -> 0.36903493 | J78: =1-(K32/C$28) -> 0.38388117 | K78: =1-(L32/C$28) -> 0.39872741 | L78: =1-(M32/C$28) -> 0.41357364 | M78: =1-(N32/C$28) -> 0.42841988 | N78: =1-(O32/C$28) -> 0.44326612
A79: =A33 -> 6000 | B79: =1-(C33/C$28) -> 0.25461316 | C79: =1-(D33/C$28) -> 0.27697477 | D79: =1-(E33/C$28) -> 0.2918825 | E79: =1-(F33/C$28) -> 0.30679024 | F79: =1-(G33/C$28) -> 0.32169798 | G79: =1-(H33/C$28) -> 0.33660571 | H79: =1-(I33/C$28) -> 0.35151345 | I79: =1-(J33/C$28) -> 0.36642119 | J79: =1-(K33/C$28) -> 0.38132892 | K79: =1-(L33/C$28) -> 0.39623666 | L79: =1-(M33/C$28) -> 0.4111444 | M79: =1-(N33/C$28) -> 0.42605213 | N79: =1-(O33/C$28) -> 0.44095987
A80: =A34 -> 7000 | B80: =1-(C34/C$28) -> 0.25255663 | C80: =1-(D34/C$28) -> 0.27497993 | D80: =1-(E34/C$28) -> 0.2899288 | E80: =1-(F34/C$28) -> 0.30487766 | F80: =1-(G34/C$28) -> 0.31982653 | G80: =1-(H34/C$28) -> 0.3347754 | H80: =1-(I34/C$28) -> 0.34972427 | I80: =1-(J34/C$28) -> 0.36467313 | J80: =1-(K34/C$28) -> 0.379622 | K80: =1-(L34/C$28) -> 0.39457087 | L80: =1-(M34/C$28) -> 0.40951974 | M80: =1-(N34/C$28) -> 0.4244686 | N80: =1-(O34/C$28) -> 0.43941747
A81: =A35 -> 8000 | B81: =1-(C35/C$28) -> 0.25665994 | C81: =1-(D35/C$28) -> 0.27896014 | D81: =1-(E35/C$28) -> 0.29382694 | E81: =1-(F35/C$28) -> 0.30869374 | F81: =1-(G35/C$28) -> 0.32356054 | G81: =1-(H35/C$28) -> 0.33842735 | H81: =1-(I35/C$28) -> 0.35329415 | I81: =1-(J35/C$28) -> 0.36816095 | J81: =1-(K35/C$28) -> 0.38302775 | K81: =1-(L35/C$28) -> 0.39789455 | L81: =1-(M35/C$28) -> 0.41276135 | M81: =1-(N35/C$28) -> 0.42762815 | N81: =1-(O35/C$28) -> 0.44249495
A82: =A36 -> 9000 | B82: =1-(C36/C$28) -> 0.25472419 | C82: =1-(D36/C$28) -> 0.27708246 | D82: =1-(E36/C$28) -> 0.29198798 | E82: =1-(F36/C$28) -> 0.30689349 | F82: =1-(G36/C$28) -> 0.32179901 | G82: =1-(H36/C$28) -> 0.33670453 | H82: =1-(I36/C$28) -> 0.35161004 | I82: =1-(J36/C$28) -> 0.36651556 | J82: =1-(K36/C$28) -> 0.38142108 | K82: =1-(L36/C$28) -> 0.39632659 | L82: =1-(M36/C$28) -> 0.41123211 | M82: =1-(N36/C$28) -> 0.42613762 | N82: =1-(O36/C$28) -> 0.44104314
A83: =A37 -> 10000 | B83: =1-(C37/C$28) -> 0.31282825 | C83: =1-(D37/C$28) -> 0.3334434 | D83: =1-(E37/C$28) -> 0.34718684 | E83: =1-(F37/C$28) -> 0.36093027 | F83: =1-(G37/C$28) -> 0.37467371 | G83: =1-(H37/C$28) -> 0.38841714 | H83: =1-(I37/C$28) -> 0.40216058 | I83: =1-(J37/C$28) -> 0.41590401 | J83: =1-(K37/C$28) -> 0.42964745 | K83: =1-(L37/C$28) -> 0.44339088 | L83: =1-(M37/C$28) -> 0.45713432 | M83: =1-(N37/C$28) -> 0.47087775 | N83: =1-(O37/C$28) -> 0.48462119
A84: =A38 -> 11000 | B84: =1-(C38/C$28) -> 0.30105483 | C84: =1-(D38/C$28) -> 0.32202319 | D84: =1-(E38/C$28) -> 0.33600209 | E84: =1-(F38/C$28) -> 0.349981 | F84: =1-(G38/C$28) -> 0.3639599 | G84: =1-(H38/C$28) -> 0.3779388 | H84: =1-(I38/C$28) -> 0.39191771 | I84: =1-(J38/C$28) -> 0.40589661 | J84: =1-(K38/C$28) -> 0.41987551 | K84: =1-(L38/C$28) -> 0.43385442 | L84: =1-(M38/C$28) -> 0.44783332 | M84: =1-(N38/C$28) -> 0.46181222 | N84: =1-(O38/C$28) -> 0.47579113
A85: =A39 -> 12000 | B85: =1-(C39/C$28) -> 0.30094795 | C85: =1-(D39/C$28) -> 0.32191951 | D85: =1-(E39/C$28) -> 0.33590055 | E85: =1-(F39/C$28) -> 0.34988159 | F85: =1-(G39/C$28) -> 0.36386263 | G85: =1-(H39/C$28) -> 0.37784367 | H85: =1-(I39/C$28) -> 0.39182471 | I85: =1-(J39/C$28) -> 0.40580575 | J85: =1-(K39/C$28) -> 0.4197868 | K85: =1-(L39/C$28) -> 0.43376784 | L85: =1-(M39/C$28) -> 0.44774888 | M85: =1-(N39/C$28) -> 0.46172992 | N85: =1-(O39/C$28) -> 0.47571096
... A93: =A47 -> 20000 | B93: =1-(C47/C$28) -> 0.31905852 | C93: =1-(D47/C$28) -> 0.33948676 | D93: =1-(E47/C$28) -> 0.35310559 | E93: =1-(F47/C$28) -> 0.36672442 | F93: =1-(G47/C$28) -> 0.38034325 | G93: =1-(H47/C$28) -> 0.39396208 | H93: =1-(I47/C$28) -> 0.40758091 | I93: =1-(J47/C$28) -> 0.42119974 | J93: =1-(K47/C$28) -> 0.43481857 | K93: =1-(L47/C$28) -> 0.4484374 | L93: =1-(M47/C$28) -> 0.46205623 | M93: =1-(N47/C$28) -> 0.47567506 | N93: =1-(O47/C$28) -> 0.48929389
